setup.py
src/streamcorpus_factorie/__init__.py
src/streamcorpus_factorie/_factorie.py
src/streamcorpus_factorie.egg-info/PKG-INFO
src/streamcorpus_factorie.egg-info/SOURCES.txt
src/streamcorpus_factorie.egg-info/dependency_links.txt
src/streamcorpus_factorie.egg-info/entry_points.txt
src/streamcorpus_factorie.egg-info/requires.txt
src/streamcorpus_factorie.egg-info/top_level.txt