Metadata-Version: 1.1
Name: streamcorpus-factorie
Version: 0.1.0
Summary: Tools for building streamcorpus objects for particular collections of text used in TREC KBA.
Home-page: UNKNOWN
Author: Diffeo, Inc.
Author-email: support@diffeo.com
License: MIT/X11 license http://opensource.org/licenses/MIT
Platform: UNKNOWN
Classifier: Development Status :: 3 - Alpha
Classifier: Topic :: Utilities
Classifier: License :: OSI Approved :: MIT License
